gai_tool/__init__.py
gai_tool/api/__init__.py
gai_tool/api/gemini_client.py
gai_tool/api/github_api.py
gai_tool/api/gitlab_api.py
gai_tool/api/groq_api.py
gai_tool/api/hugging_client.py
gai_tool/api/ollama_client.py
gai_tool/api/token_counter_lite.py
gai_tool/main.py
gai_tool/src/__init__.py
gai_tool/src/commits.py
gai_tool/src/display_choices.py
gai_tool/src/merge_requests.py
gai_tool/src/myconfig.py
gai_tool/src/prompts.py
gai_tool/src/utils.py
gai_tool-0.5.3.dist-info/LICENSE
gai_tool-0.5.3.dist-info/METADATA
gai_tool-0.5.3.dist-info/WHEEL
gai_tool-0.5.3.dist-info/entry_points.txt
gai_tool-0.5.3.dist-info/RECORD
