Metadata-Version: 2.3
Name: gai-tool
Version: 0.5.3
Summary: AI-Powered Automation Tool for Git 🚀
Author: Daniel Ratmiroff
Author-email: danielratmiroff@pm.me
Requires-Python: >=3.12,<4.0
Classifier: Programming Language :: Python :: 3
Classifier: Programming Language :: Python :: 3.12
Classifier: Programming Language :: Python :: 3.13
Requires-Dist: appdirs (>=1.4.4,<2.0.0)
Requires-Dist: build (>=1.2.2.post1,<2.0.0)
Requires-Dist: codecov (>=2.1.13,<3.0.0)
Requires-Dist: colorama (>=0.4.6,<0.5.0)
Requires-Dist: groq (>=0.18.0,<0.19.0)
Requires-Dist: huggingface-hub (>=0.29.1,<0.30.0)
Requires-Dist: langchain-community (>=0.3.18,<0.4.0)
Requires-Dist: langchain-core (>=0.3.37,<0.4.0)
Requires-Dist: langchain-google-genai (>=2.0.10,<3.0.0)
Requires-Dist: langchain-ollama (>=0.2.3,<0.3.0)
Requires-Dist: ollama (>=0.4.7,<0.5.0)
Requires-Dist: pick (>=2.4.0,<3.0.0)
Requires-Dist: pygithub (>=2.6.1,<3.0.0)
Requires-Dist: pytest (>=8.3.4,<9.0.0)
Requires-Dist: pytest-cov (>=4.1.0,<5.0.0)
Requires-Dist: python-gitlab (>=5.6.0,<6.0.0)
Requires-Dist: requests (>=2.32.3,<3.0.0)
Requires-Dist: rich (>=13.9.4,<14.0.0)
Requires-Dist: tokenizers (>=0.21.0,<0.22.0)
Requires-Dist: twine (>=6.1.0,<7.0.0)
Requires-Dist: wheel (>=0.45.1,<0.46.0)
Requires-Dist: zipp (>=3.21.0,<4.0.0)
Project-URL: documentation, https://github.com/Danielratmiroff/gai#readme
Project-URL: homepage, https://github.com/Danielratmiroff/gai
Project-URL: issues, https://github.com/Danielratmiroff/gai/issues
Project-URL: repository, https://github.com/Danielratmiroff/gai
